factli/__init__.py
factli/factli.py
factli/get_leaderboard.py
factli/get_list.py
factli/get_lists.R
factli/get_posts.py
factli-0.2.0.dist-info/entry_points.txt
factli-0.2.0.dist-info/LICENSE
factli-0.2.0.dist-info/WHEEL
factli-0.2.0.dist-info/METADATA
factli-0.2.0.dist-info/RECORD
