Metadata-Version: 2.1
Name: factli
Version: 0.2.0
Summary: A Facebook Crowdtangle Client
Home-page: https://github.com/Leibniz-HBI/DBoeS-stats
License: MIT
Author: Aditya Kumar
Author-email: a.kumar@leibniz-hbi.de
Requires-Python: >=3.8,<4.0
Classifier: License :: OSI Approved :: MIT License
Classifier: Programming Language :: Python :: 3
Classifier: Programming Language :: Python :: 3.8
Classifier: Programming Language :: Python :: 3.9
Requires-Dist: click (>=8.0.1,<9.0.0)
Requires-Dist: loguru (>=0.5.3,<0.6.0)
Requires-Dist: pandas (>=1.2.4,<2.0.0)
Requires-Dist: requests (>=2.25.1,<3.0.0)
Requires-Dist: schedule (>=1.1.0,<2.0.0)
Requires-Dist: yagmail (>=0.14.256,<0.15.0)
Project-URL: Repository, https://github.com/Leibniz-HBI/DBoeS-stats
